Workbook

Sheet Lisez-moi
A1: Étude socio-économique et environnementale — Valorisation des déchets plastiques en pavés préfabriqués
A3: STATUT DE CE DOCUMENT
A4: Ce classeur reconstitue, à des fins de démonstration de compétences (portfolio professionnel), la méthodologie et les données d'une étude réellement menée par Joël AGBANLIN dans le cadre de son mémoire de Licence en Économie Appliquée (FASEG-UAC, 2016), avec l'appui de CISE SARL.
A5: Ce classeur reconstitue, à des fins de démonstration de compétences (portfolio professionnel), la méthodologie et les données d'une étude réellement menée par Joël AGBANLIN dans le cadre de son mémoire de Licence en Économie Appliquée (FASEG-UAC, 2016), avec l'appui de CISE SARL.
A6: Les données individuelles présentées dans l'onglet "Données ménages" sont SIMULÉES : elles reproduisent des tendances plausibles pour ce type d'enquête, mais ne sont pas les données brutes originales du mémoire (non conservées). La structure de l'enquête, les variables et les indicateurs correspondent en revanche à la méthodologie réellement appliquée.
A8: CONTEXTE
A9: L'étude visait à évaluer le potentiel de collecte et de valorisation des déchets plastiques à Cotonou, à travers une filière de transformation en pavés préfabriqués (économie circulaire), et à mesurer l'acceptabilité socio-économique de cette filière auprès des ménages, des collecteurs informels et des artisans.
A11: MÉTHODOLOGIE ET LIMITES
A12: - Échantillon : 120 ménages enquêtés sur 3 quartiers de Cotonou (Akpakpa, Dantokpa, Fidjrossè), à raison de 40 ménages par quartier.
A13: - Méthode d'échantillonnage : échantillonnage de convenance (non probabiliste), en raison des moyens limités d'une étude de mémoire de licence.
A14: - Limite assumée : cet échantillon ne permet pas une généralisation statistique à l'ensemble de la population de Cotonou (~700 000 habitants). Il fournit des tendances indicatives locales, robustes à l'échelle des 3 quartiers enquêtés.
A15: - Un volet qualitatif complémentaire (entretiens avec collecteurs informels et artisans) a permis de trianguler les résultats quantitatifs.
... A28: Voir l'onglet "Acteurs chaîne de valeur" (nouveau) et la section correspondante de l'onglet "Indicateurs MEAL" pour le détail.

Sheet Données ménages
A1: ID | B1: Quartier | C1: Taille du ménage | D1: Production déchets plastiques (fréquence) | E1: Pratique le tri à la source (Oui/Non) | F1: Disposé à vendre le plastique trié (Oui/Non/Incertain) | G1: Connaît la filière pavé recyclé (Oui/Non) | H1: Disposé à acheter un pavé recyclé (Oui/Non/Incertain) | I1: Revenu mensuel estimé (FCFA)
A2: 1 | B2: Akpakpa | C2: 3 | D2: Quotidienne | E2: Oui | F2: Oui | G2: Non | H2: Incertain | I2: 45000
A3: 2 | B3: Akpakpa | C3: 6 | D3: Quotidienne | E3: Oui | F3: Oui | G3: Non | H3: Non | I3: 130000
A4: 3 | B4: Akpakpa | C4: 4 | D4: Quotidienne | E4: Oui | F4: Incertain | G4: Non | H4: Oui | I4: 130000
A5: 4 | B5: Akpakpa | C5: 5 | D5: Quotidienne | E5: Oui | F5: Non | G5: Oui | H5: Oui | I5: 110000
A6: 5 | B6: Akpakpa | C6: 5 | D6: Hebdomadaire | E6: Non | F6: Incertain | G6: Non | H6: Incertain | I6: 130000
A7: 6 | B7: Akpakpa | C7: 3 | D7: Hebdomadaire | E7: Non | F7: Non | G7: Non | H7: Non | I7: 45000
A8: 7 | B8: Akpakpa | C8: 2 | D8: Hebdomadaire | E8: Non | F8: Incertain | G8: Non | H8: Incertain | I8: 130000
A9: 8 | B9: Akpakpa | C9: 5 | D9: Quotidienne | E9: Non | F9: Oui | G9: Non | H9: Incertain | I9: 45000
A10: 9 | B10: Akpakpa | C10: 4 | D10: Hebdomadaire | E10: Oui | F10: Oui | G10: Oui | H10: Incertain | I10: 75000
A11: 10 | B11: Akpakpa | C11: 5 | D11: Hebdomadaire | E11: Non | F11: Oui | G11: Oui | H11: Oui | I11: 90000
A12: 11 | B12: Akpakpa | C12: 3 | D12: Quotidienne | E12: Non | F12: Incertain | G12: Non | H12: Incertain | I12: 130000
A13: 12 | B13: Akpakpa | C13: 7 | D13: Quotidienne | E13: Oui | F13: Non | G13: Non | H13: Incertain | I13: 130000
... A121: 120 | B121: Fidjrossè | C121: 4 | D121: Hebdomadaire | E121: Oui | F121: Non | G121: Oui | H121: Oui | I121: 130000

Sheet Indicateurs MEAL
A1: Indicateurs MEAL — calculés automatiquement à partir de l'onglet "Données ménages"
A3: Indicateur | B3: Akpakpa | C3: Dantokpa | D3: Fidjrossè | E3: Ensemble (N=120) | F3: Définition / Cible
A4: Taux de tri des déchets à la source | B4: =COUNTIFS('Données ménages'!$B$2:$B$121,"Akpakpa",'Données ménages'!$E$2:$E$121,"Oui")/COUNTIF('Données ménages'!$B$2:$B$121,"Akpakpa") -> 0.275 | C4: =COUNTIFS('Données ménages'!$B$2:$B$121,"Dantokpa",'Données ménages'!$E$2:$E$121,"Oui")/COUNTIF('Données ménages'!$B$2:$B$121,"Dantokpa") -> 0.475 | D4: =COUNTIFS('Données ménages'!$B$2:$B$121,"Fidjrossè",'Données ménages'!$E$2:$E$121,"Oui")/COUNTIF('Données ménages'!$B$2:$B$121,"Fidjrossè") -> 0.5 | E4: =AVERAGE(B4:D4) -> 0.41666667 | F4: % de ménages enquêtés pratiquant un tri à la source. Cible indicative : ≥ 40%.
A5: Taux de disposition à vendre le plastique trié | B5: =COUNTIFS('Données ménages'!$B$2:$B$121,"Akpakpa",'Données ménages'!$F$2:$F$121,"Oui")/COUNTIF('Données ménages'!$B$2:$B$121,"Akpakpa") -> 0.4 | C5: =COUNTIFS('Données ménages'!$B$2:$B$121,"Dantokpa",'Données ménages'!$F$2:$F$121,"Oui")/COUNTIF('Données ménages'!$B$2:$B$121,"Dantokpa") -> 0.5 | D5: =COUNTIFS('Données ménages'!$B$2:$B$121,"Fidjrossè",'Données ménages'!$F$2:$F$121,"Oui")/COUNTIF('Données ménages'!$B$2:$B$121,"Fidjrossè") -> 0.5 | E5: =AVERAGE(B5:D5) -> 0.46666667 | F5: % de ménages disposés à vendre leur plastique trié à un collecteur.
A6: Taux de connaissance de la filière pavé recyclé | B6: =COUNTIFS('Données ménages'!$B$2:$B$121,"Akpakpa",'Données ménages'!$G$2:$G$121,"Oui")/COUNTIF('Données ménages'!$B$2:$B$121,"Akpakpa") -> 0.25 | C6: =COUNTIFS('Données ménages'!$B$2:$B$121,"Dantokpa",'Données ménages'!$G$2:$G$121,"Oui")/COUNTIF('Données ménages'!$B$2:$B$121,"Dantokpa") -> 0.45 | D6: =COUNTIFS('Données ménages'!$B$2:$B$121,"Fidjrossè",'Données ménages'!$G$2:$G$121,"Oui")/COUNTIF('Données ménages'!$B$2:$B$121,"Fidjrossè") -> 0.275 | E6: =AVERAGE(B6:D6) -> 0.325 | F6: % de ménages connaissant l'existence de la filière de valorisation en pavés.
A7: Taux d'acceptabilité d'achat d'un pavé recyclé | B7: =COUNTIFS('Données ménages'!$B$2:$B$121,"Akpakpa",'Données ménages'!$H$2:$H$121,"Oui")/COUNTIF('Données ménages'!$B$2:$B$121,"Akpakpa") -> 0.45 | C7: =COUNTIFS('Données ménages'!$B$2:$B$121,"Dantokpa",'Données ménages'!$H$2:$H$121,"Oui")/COUNTIF('Données ménages'!$B$2:$B$121,"Dantokpa") -> 0.55 | D7: =COUNTIFS('Données ménages'!$B$2:$B$121,"Fidjrossè",'Données ménages'!$H$2:$H$121,"Oui")/COUNTIF('Données ménages'!$B$2:$B$121,"Fidjrossè") -> 0.425 | E7: =AVERAGE(B7:D7) -> 0.475 | F7: % de ménages favorables à l'achat d'un pavé fabriqué à partir de plastique recyclé. Cible indicative : ≥ 60%.
A9: Note méthodologique : échantillon de convenance (N=120, 3 quartiers), non probabiliste. Résultats indicatifs, non généralisables statistiquement à l'ensemble de Cotonou.
A11: Effets potentiels sur l'emploi, les revenus et l'environnement (scénario projeté)
A12: Indicateur | B12: Collecteurs | C12: Artisans | D12: Ensemble | F12: Définition / Cible
A13: Emplois recensés dans l'échantillon (N) | B13: =COUNTIF('Acteurs chaîne de valeur'!$B$5:$B$29,"Collecteur") -> 15 | C13: =COUNTIF('Acteurs chaîne de valeur'!$B$5:$B$29,"Artisan") -> 10 | D13: =B13+C13 -> 25 | F13: Nombre de métiers/emplois de la chaîne représentés dans l'échantillon d'acteurs enquêtés.
A14: Gain de revenu potentiel moyen (%) | B14: =AVERAGEIF('Acteurs chaîne de valeur'!$B$5:$B$29,"Collecteur",'Acteurs chaîne de valeur'!$G$5:$G$29) -> 0.19086667 | C14: =AVERAGEIF('Acteurs chaîne de valeur'!$B$5:$B$29,"Artisan",'Acteurs chaîne de valeur'!$G$5:$G$29) -> 0.2156 | D14: =AVERAGE('Acteurs chaîne de valeur'!$G$5:$G$29) -> 0.20076 | F14: Variation estimée du revenu si l'acteur rejoint une filière structurée (scénario projeté, +15-25%).
A15: Volume de plastique traité (kg/mois, échantillon) | B15: =SUMIF('Acteurs chaîne de valeur'!$B$5:$B$29,"Collecteur",'Acteurs chaîne de valeur'!$H$5:$H$29) -> 4200 | C15: =SUMIF('Acteurs chaîne de valeur'!$B$5:$B$29,"Artisan",'Acteurs chaîne de valeur'!$H$5:$H$29) -> 2200 | D15: =B15+C15 -> 6400 | F15: Volume de plastique traité/mois par les acteurs enquêtés — proxy de la quantité détournée de l'environnement urbain (caniveaux, décharges).
A17: Prudence méthodologique : indicateurs d'emploi/revenu/environnement basés sur un échantillon restreint (N=25 acteurs) et un scénario projeté, non une mesure d'impact observée. À ne présenter que comme un potentiel indicatif, cohérent avec des initiatives comparables.

Sheet Guide entretiens qualitatifs
A1: Guide d'entretien semi-structuré — Collecteurs informels et artisans (volet qualitatif)
A3: Cible : 10 à 15 entretiens semi-structurés (collecteurs informels de déchets plastiques, artisans potentiellement impliqués dans la transformation).
A5: Axe 1 — Pratiques actuelles de collecte
A6: 1. Depuis combien de temps exercez-vous cette activité de collecte ?
A7: 2. Quels types de déchets collectez-vous et auprès de qui ?
A8: 3. Comment écoulez-vous actuellement le plastique collecté ?
A10: Axe 2 — Perception de la filière pavé recyclé
A11: 4. Avez-vous déjà entendu parler de la transformation du plastique en pavés ?
A12: 5. Quels avantages ou freins voyez-vous à une telle filière ?
A13: 6. Seriez-vous prêt à vendre votre plastique collecté à une unité de transformation ?
A15: Axe 3 — Conditions économiques et contraintes
A16: 7. Quel est le principal frein à l'intensification de votre activité de collecte ?
... A19: Note : les réponses à ces entretiens ne sont pas simulées en verbatim dans ce classeur — seule la trame d'entretien est fournie. Dans un vrai rapport, cette section serait complétée par une synthèse thématique des propos recueillis (jamais par des citations inventées attribuées à des personnes réelles).

Sheet Acteurs chaîne de valeur
A1: Scénario potentiel — Emploi et revenus dans une filière structurée de valorisation
A2: Note : ces données sont un SCÉNARIO PROJETÉ (potentiel estimé), pas une mesure d'impact réelle — la filière structurée n'existait pas au moment de l'étude. "Revenu actuel" reflète l'activité informelle telle qu'observée ; "revenu potentiel" est une projection à +15-25% si l'acteur était intégré à une filière organisée de collecte-transformation, hypothèse cohérente avec des initiatives comparables d'économie circulaire en Afrique de l'Ouest.
A4: ID | B4: Type d'acteur | C4: Ancienneté (années) | D4: Heures / semaine | E4: Revenu actuel (FCFA/mois) | F4: Revenu potentiel estimé (FCFA/mois) | G4: Variation potentielle (%) | H4: Volume plastique traité (kg/mois)
A5: 1 | B5: Collecteur | C5: 3 | D5: 30 | E5: 28000 | F5: =E5*(1+0.155) -> 32340 | G5: =(F5-E5)/E5 -> 0.155 | H5: 400
A6: 2 | B6: Collecteur | C6: 8 | D6: 45 | E6: 18000 | F6: =E6*(1+0.208) -> 21744 | G6: =(F6-E6)/E6 -> 0.208 | H6: 250
A7: 3 | B7: Collecteur | C7: 5 | D7: 30 | E7: 18000 | F7: =E7*(1+0.193) -> 21474 | G7: =(F7-E7)/E7 -> 0.193 | H7: 150
A8: 4 | B8: Collecteur | C8: 1 | D8: 30 | E8: 18000 | F8: =E8*(1+0.192) -> 21456 | G8: =(F8-E8)/E8 -> 0.192 | H8: 350
A9: 5 | B9: Collecteur | C9: 8 | D9: 45 | E9: 18000 | F9: =E9*(1+0.213) -> 21834 | G9: =(F9-E9)/E9 -> 0.213 | H9: 200
A10: 6 | B10: Collecteur | C10: 5 | D10: 25 | E10: 32000 | F10: =E10*(1+0.19) -> 38080 | G10: =(F10-E10)/E10 -> 0.19 | H10: 350
A11: 7 | B11: Collecteur | C11: 2 | D11: 25 | E11: 32000 | F11: =E11*(1+0.163) -> 37216 | G11: =(F11-E11)/E11 -> 0.163 | H11: 450
A12: 8 | B12: Collecteur | C12: 4 | D12: 30 | E12: 32000 | F12: =E12*(1+0.207) -> 38624 | G12: =(F12-E12)/E12 -> 0.207 | H12: 150
A13: 9 | B13: Collecteur | C13: 5 | D13: 50 | E13: 22000 | F13: =E13*(1+0.208) -> 26576 | G13: =(F13-E13)/E13 -> 0.208 | H13: 150
A14: 10 | B14: Collecteur | C14: 6 | D14: 30 | E14: 25000 | F14: =E14*(1+0.205) -> 30125 | G14: =(F14-E14)/E14 -> 0.205 | H14: 150
A15: 11 | B15: Collecteur | C15: 1 | D15: 45 | E15: 18000 | F15: =E15*(1+0.171) -> 21078 | G15: =(F15-E15)/E15 -> 0.171 | H15: 350
A16: 12 | B16: Collecteur | C16: 6 | D16: 45 | E16: 28000 | F16: =E16*(1+0.181) -> 33068 | G16: =(F16-E16)/E16 -> 0.181 | H16: 450
A17: 13 | B17: Collecteur | C17: 5 | D17: 40 | E17: 25000 | F17: =E17*(1+0.175) -> 29375 | G17: =(F17-E17)/E17 -> 0.175 | H17: 250
A18: 14 | B18: Collecteur | C18: 2 | D18: 50 | E18: 22000 | F18: =E18*(1+0.207) -> 26554 | G18: =(F18-E18)/E18 -> 0.207 | H18: 150
A19: 15 | B19: Collecteur | C19: 5 | D19: 40 | E19: 25000 | F19: =E19*(1+0.195) -> 29875 | G19: =(F19-E19)/E19 -> 0.195 | H19: 400
A20: 16 | B20: Artisan | C20: 5 | D20: 20 | E20: 28000 | F20: =E20*(1+0.192) -> 33376 | G20: =(F20-E20)/E20 -> 0.192 | H20: 300
A21: 17 | B21: Artisan | C21: 8 | D21: 30 | E21: 32000 | F21: =E21*(1+0.192) -> 38144 | G21: =(F21-E21)/E21 -> 0.192 | H21: 250
A22: 18 | B22: Artisan | C22: 6 | D22: 20 | E22: 48000 | F22: =E22*(1+0.229) -> 58992 | G22: =(F22-E22)/E22 -> 0.229 | H22: 300
A23: 19 | B23: Artisan | C23: 8 | D23: 30 | E23: 38000 | F23: =E23*(1+0.209) -> 45942 | G23: =(F23-E23)/E23 -> 0.209 | H23: 200
A24: 20 | B24: Artisan | C24: 5 | D24: 35 | E24: 28000 | F24: =E24*(1+0.244) -> 34832 | G24: =(F24-E24)/E24 -> 0.244 | H24: 100
A25: 21 | B25: Artisan | C25: 4 | D25: 20 | E25: 28000 | F25: =E25*(1+0.215) -> 34020 | G25: =(F25-E25)/E25 -> 0.215 | H25: 200
A26: 22 | B26: Artisan | C26: 6 | D26: 35 | E26: 38000 | F26: =E26*(1+0.239) -> 47082 | G26: =(F26-E26)/E26 -> 0.239 | H26: 250
A27: 23 | B27: Artisan | C27: 3 | D27: 20 | E27: 42000 | F27: =E27*(1+0.167) -> 49014 | G27: =(F27-E27)/E27 -> 0.167 | H27: 200
A28: 24 | B28: Artisan | C28: 1 | D28: 35 | E28: 28000 | F28: =E28*(1+0.227) -> 34356 | G28: =(F28-E28)/E28 -> 0.227 | H28: 150
A29: 25 | B29: Artisan | C29: 2 | D29: 25 | E29: 42000 | F29: =E29*(1+0.242) -> 52164 | G29: =(F29-E29)/E29 -> 0.242 | H29: 250
